ganblr/__init__.py
ganblr/kdb.py
ganblr/utils.py
ganblr/models/__init__.py
ganblr/models/ganblr.py
ganblr/models/ganblrmug.py
ganblr/models/ganblrpp.py
ganblr/pyitlib/__init__.py
ganblr/pyitlib/pyitlib/__init__.py
ganblr/pyitlib/pyitlib/discrete_random_variable.py
ganblr/pyitlib/pyitlib/pyitlib_version.py
ganblr/pyitlib/pyitlib/util.py
ganblr-0.1.3.dist-info/LICENSE
ganblr-0.1.3.dist-info/METADATA
ganblr-0.1.3.dist-info/WHEEL
ganblr-0.1.3.dist-info/top_level.txt
ganblr-0.1.3.dist-info/RECORD
