Metadata-Version: 2.1
Name: ganblr
Version: 0.1.3
Summary: Ganblr Toolbox
Home-page: https://github.com/tulip-lab/ganblr
Author: kae zhou
Author-email: kaezhou@gmail.com
License: MIT Licence
Keywords: ganblr,tulip
Platform: any
Classifier: Programming Language :: Python :: 3
Classifier: License :: OSI Approved :: MIT License
Classifier: Operating System :: OS Independent
Requires-Python: >=3.5.0
License-File: LICENSE
Requires-Dist: numpy
Requires-Dist: pandas
Requires-Dist: tensorflow (>=2.3)
Requires-Dist: scikit-learn (>=0.24)
Requires-Dist: pgmpy
